<?xml version="1.0" encoding="UTF-8" ?>
<lfm status="ok"><topalbums artist="Billie Eilish" page="1" perPage="50" totalPages="168" total="8370"><album><name>when we all fall asleep, where do we go?</name>
<playcount>34238942</playcount>
<url>https://www.last.fm/music/Billie+Eilish/when+we+all+fall+asleep,+where+do+we+go%3F</url>
<artist><name>Billie Eilish</name>
<url>https://www.last.fm/music/Billie+Eilish</url>
</artist>
<image size="small">https://lastfm.freetls.fastly.net/i/u/34s/e293a236bd4c60f12b8cf9dab8c0ac9f.png</image>
<image size="medium">https://lastfm.freetls.fastly.net/i/u/64s/e293a236bd4c60f12b8cf9dab8c0ac9f.png</image>
<image size="large">https://lastfm.freetls.fastly.net/i/u/174s/e293a236bd4c60f12b8cf9dab8c0ac9f.png</image>
<image size="extralarge">https://lastfm.freetls.fastly.net/i/u/300x300/e293a236bd4c60f12b8cf9dab8c0ac9f.png</image>
</album>
<album><name>dont smile at me</name>
<playcount>13671192</playcount>
<url>https://www.last.fm/music/Billie+Eilish/dont+smile+at+me</url>
<artist><name>Billie Eilish</name>
<url>https://www.last.fm/music/Billie+Eilish</url>
</artist>
<image size="small">https://lastfm.freetls.fastly.net/i/u/34s/271b0a5eaeda187d5d768e3b4310fa3f.png</image>
<image size="medium">https://lastfm.freetls.fastly.net/i/u/64s/271b0a5eaeda187d5d768e3b4310fa3f.png</image>
<image size="large">https://lastfm.freetls.fastly.net/i/u/174s/271b0a5eaeda187d5d768e3b4310fa3f.png</image>
<image size="extralarge">https://lastfm.freetls.fastly.net/i/u/300x300/271b0a5eaeda187d5d768e3b4310fa3f.png</image>
</album>
<album><name>everything i wanted</name>
<playcount>3811838</playcount>
<url>https://www.last.fm/music/Billie+Eilish/everything+i+wanted</url>
<artist><name>Billie Eilish</name>
<url>https://www.last.fm/music/Billie+Eilish</url>
</artist>
<image size="small">https://lastfm.freetls.fastly.net/i/u/34s/23ff44b6c1b5c3b2ba6d11684493004a.png</image>
<image size="medium">https://lastfm.freetls.fastly.net/i/u/64s/23ff44b6c1b5c3b2ba6d11684493004a.png</image>
<image size="large">https://lastfm.freetls.fastly.net/i/u/174s/23ff44b6c1b5c3b2ba6d11684493004a.png</image>
<image size="extralarge">https://lastfm.freetls.fastly.net/i/u/300x300/23ff44b6c1b5c3b2ba6d11684493004a.png</image>
</album>
<album><name>lovely (with Khalid)</name>
<playcount>3109438</playcount>
<url>https://www.last.fm/music/Billie+Eilish/lovely+(with+Khalid)</url>
<artist><name>Billie Eilish</name>
<url>https://www.last.fm/music/Billie+Eilish</url>
</artist>
<image size="small">https://lastfm.freetls.fastly.net/i/u/34s/d14b594f15b5629a3ba686cab2c95f83.png</image>
<image size="medium">https://lastfm.freetls.fastly.net/i/u/64s/d14b594f15b5629a3ba686cab2c95f83.png</image>
<image size="large">https://lastfm.freetls.fastly.net/i/u/174s/d14b594f15b5629a3ba686cab2c95f83.png</image>
<image size="extralarge">https://lastfm.freetls.fastly.net/i/u/300x300/d14b594f15b5629a3ba686cab2c95f83.png</image>
</album>
<album><name>no time to die</name>
<playcount>1519824</playcount>
<url>https://www.last.fm/music/Billie+Eilish/no+time+to+die</url>
<artist><name>Billie Eilish</name>
<url>https://www.last.fm/music/Billie+Eilish</url>
</artist>
<image size="small">https://lastfm.freetls.fastly.net/i/u/34s/e4bf7a43068384ce9fd392e77e93ee8d.png</image>
<image size="medium">https://lastfm.freetls.fastly.net/i/u/64s/e4bf7a43068384ce9fd392e77e93ee8d.png</image>
<image size="large">https://lastfm.freetls.fastly.net/i/u/174s/e4bf7a43068384ce9fd392e77e93ee8d.png</image>
<image size="extralarge">https://lastfm.freetls.fastly.net/i/u/300x300/e4bf7a43068384ce9fd392e77e93ee8d.png</image>
</album>
<album><name>Bellyache</name>
<playcount>1451027</playcount>
<url>https://www.last.fm/music/Billie+Eilish/Bellyache</url>
<artist><name>Billie Eilish</name>
<url>https://www.last.fm/music/Billie+Eilish</url>
</artist>
<image size="small">https://lastfm.freetls.fastly.net/i/u/34s/4935581115ed357eda764e75997a48ac.png</image>
<image size="medium">https://lastfm.freetls.fastly.net/i/u/64s/4935581115ed357eda764e75997a48ac.png</image>
<image size="large">https://lastfm.freetls.fastly.net/i/u/174s/4935581115ed357eda764e75997a48ac.png</image>
<image size="extralarge">https://lastfm.freetls.fastly.net/i/u/300x300/4935581115ed357eda764e75997a48ac.png</image>
</album>
<album><name>When The Party&apos;s Over</name>
<playcount>1571297</playcount>
<url>https://www.last.fm/music/Billie+Eilish/When+The+Party%27s+Over</url>
<artist><name>Billie Eilish</name>
<url>https://www.last.fm/music/Billie+Eilish</url>
</artist>
<image size="small">https://lastfm.freetls.fastly.net/i/u/34s/5dee126526b4cec3e68f76e719d43c22.png</image>
<image size="medium">https://lastfm.freetls.fastly.net/i/u/64s/5dee126526b4cec3e68f76e719d43c22.png</image>
<image size="large">https://lastfm.freetls.fastly.net/i/u/174s/5dee126526b4cec3e68f76e719d43c22.png</image>
<image size="extralarge">https://lastfm.freetls.fastly.net/i/u/300x300/5dee126526b4cec3e68f76e719d43c22.png</image>
</album>
<album><name>my future</name>
<playcount>1097474</playcount>
<url>https://www.last.fm/music/Billie+Eilish/my+future</url>
<artist><name>Billie Eilish</name>
<url>https://www.last.fm/music/Billie+Eilish</url>
</artist>
<image size="small">https://lastfm.freetls.fastly.net/i/u/34s/029a35b09c6f1d3d0999afb1ff0f3d34.png</image>
<image size="medium">https://lastfm.freetls.fastly.net/i/u/64s/029a35b09c6f1d3d0999afb1ff0f3d34.png</image>
<image size="large">https://lastfm.freetls.fastly.net/i/u/174s/029a35b09c6f1d3d0999afb1ff0f3d34.png</image>
<image size="extralarge">https://lastfm.freetls.fastly.net/i/u/300x300/029a35b09c6f1d3d0999afb1ff0f3d34.png</image>
</album>
<album><name>bad guy (with Justin Bieber)</name>
<playcount>670183</playcount>
<url>https://www.last.fm/music/Billie+Eilish/bad+guy+(with+Justin+Bieber)</url>
<artist><name>Billie Eilish</name>
<url>https://www.last.fm/music/Billie+Eilish</url>
</artist>
<image size="small">https://lastfm.freetls.fastly.net/i/u/34s/04ecb35c5ef4732bd36018ac0fcbc0d7.png</image>
<image size="medium">https://lastfm.freetls.fastly.net/i/u/64s/04ecb35c5ef4732bd36018ac0fcbc0d7.png</image>
<image size="large">https://lastfm.freetls.fastly.net/i/u/174s/04ecb35c5ef4732bd36018ac0fcbc0d7.png</image>
<image size="extralarge">https://lastfm.freetls.fastly.net/i/u/300x300/04ecb35c5ef4732bd36018ac0fcbc0d7.png</image>
</album>
<album><name>bitches broken hearts</name>
<playcount>1294879</playcount>
<url>https://www.last.fm/music/Billie+Eilish/bitches+broken+hearts</url>
<artist><name>Billie Eilish</name>
<url>https://www.last.fm/music/Billie+Eilish</url>
</artist>
<image size="small">https://lastfm.freetls.fastly.net/i/u/34s/2e01f5ad1d34c9b0fff863a52823b63d.png</image>
<image size="medium">https://lastfm.freetls.fastly.net/i/u/64s/2e01f5ad1d34c9b0fff863a52823b63d.png</image>
<image size="large">https://lastfm.freetls.fastly.net/i/u/174s/2e01f5ad1d34c9b0fff863a52823b63d.png</image>
<image size="extralarge">https://lastfm.freetls.fastly.net/i/u/300x300/2e01f5ad1d34c9b0fff863a52823b63d.png</image>
</album>
<album><name>come out and play</name>
<playcount>1018552</playcount>
<url>https://www.last.fm/music/Billie+Eilish/come+out+and+play</url>
<artist><name>Billie Eilish</name>
<url>https://www.last.fm/music/Billie+Eilish</url>
</artist>
<image size="small">https://lastfm.freetls.fastly.net/i/u/34s/c3d0daed184d92f1d548f86fa38bd541.png</image>
<image size="medium">https://lastfm.freetls.fastly.net/i/u/64s/c3d0daed184d92f1d548f86fa38bd541.png</image>
<image size="large">https://lastfm.freetls.fastly.net/i/u/174s/c3d0daed184d92f1d548f86fa38bd541.png</image>
<image size="extralarge">https://lastfm.freetls.fastly.net/i/u/300x300/c3d0daed184d92f1d548f86fa38bd541.png</image>
</album>
<album><name>Six Feet Under</name>
<playcount>951107</playcount>
<url>https://www.last.fm/music/Billie+Eilish/Six+Feet+Under</url>
<artist><name>Billie Eilish</name>
<url>https://www.last.fm/music/Billie+Eilish</url>
</artist>
<image size="small">https://lastfm.freetls.fastly.net/i/u/34s/398ed3dbd32bd7dd9721695e2d187ed1.png</image>
<image size="medium">https://lastfm.freetls.fastly.net/i/u/64s/398ed3dbd32bd7dd9721695e2d187ed1.png</image>
<image size="large">https://lastfm.freetls.fastly.net/i/u/174s/398ed3dbd32bd7dd9721695e2d187ed1.png</image>
<image size="extralarge">https://lastfm.freetls.fastly.net/i/u/300x300/398ed3dbd32bd7dd9721695e2d187ed1.png</image>
</album>
<album><name>bury a friend</name>
<playcount>1157801</playcount>
<url>https://www.last.fm/music/Billie+Eilish/bury+a+friend</url>
<artist><name>Billie Eilish</name>
<url>https://www.last.fm/music/Billie+Eilish</url>
</artist>
<image size="small">https://lastfm.freetls.fastly.net/i/u/34s/1957858adef065e34eba51538f11ac32.png</image>
<image size="medium">https://lastfm.freetls.fastly.net/i/u/64s/1957858adef065e34eba51538f11ac32.png</image>
<image size="large">https://lastfm.freetls.fastly.net/i/u/174s/1957858adef065e34eba51538f11ac32.png</image>
<image size="extralarge">https://lastfm.freetls.fastly.net/i/u/300x300/1957858adef065e34eba51538f11ac32.png</image>
</album>
<album><name>you should see me in a crown</name>
<playcount>910466</playcount>
<url>https://www.last.fm/music/Billie+Eilish/you+should+see+me+in+a+crown</url>
<artist><name>Billie Eilish</name>
<url>https://www.last.fm/music/Billie+Eilish</url>
</artist>
<image size="small">https://lastfm.freetls.fastly.net/i/u/34s/81a0688889a841f68ae1c4f57c3a41ae.png</image>
<image size="medium">https://lastfm.freetls.fastly.net/i/u/64s/81a0688889a841f68ae1c4f57c3a41ae.png</image>
<image size="large">https://lastfm.freetls.fastly.net/i/u/174s/81a0688889a841f68ae1c4f57c3a41ae.png</image>
<image size="extralarge">https://lastfm.freetls.fastly.net/i/u/300x300/81a0688889a841f68ae1c4f57c3a41ae.png</image>
</album>
<album><name>Bored</name>
<playcount>753263</playcount>
<url>https://www.last.fm/music/Billie+Eilish/Bored</url>
<artist><name>Billie Eilish</name>
<url>https://www.last.fm/music/Billie+Eilish</url>
</artist>
<image size="small">https://lastfm.freetls.fastly.net/i/u/34s/8bccd9c4336ffdbe502671287bc1b85c.png</image>
<image size="medium">https://lastfm.freetls.fastly.net/i/u/64s/8bccd9c4336ffdbe502671287bc1b85c.png</image>
<image size="large">https://lastfm.freetls.fastly.net/i/u/174s/8bccd9c4336ffdbe502671287bc1b85c.png</image>
<image size="extralarge">https://lastfm.freetls.fastly.net/i/u/300x300/8bccd9c4336ffdbe502671287bc1b85c.png</image>
</album>
<album><name>Ocean Eyes (The Remixes)</name>
<playcount>727282</playcount>
<url>https://www.last.fm/music/Billie+Eilish/Ocean+Eyes+(The+Remixes)</url>
<artist><name>Billie Eilish</name>
<url>https://www.last.fm/music/Billie+Eilish</url>
</artist>
<image size="small">https://lastfm.freetls.fastly.net/i/u/34s/a12d762704e43117a8a8de27a49a3e5c.png</image>
<image size="medium">https://lastfm.freetls.fastly.net/i/u/64s/a12d762704e43117a8a8de27a49a3e5c.png</image>
<image size="large">https://lastfm.freetls.fastly.net/i/u/174s/a12d762704e43117a8a8de27a49a3e5c.png</image>
<image size="extralarge">https://lastfm.freetls.fastly.net/i/u/300x300/a12d762704e43117a8a8de27a49a3e5c.png</image>
</album>
<album><name>WHEN I WAS OLDER (Music Inspired By The Film ROMA)</name>
<playcount>556095</playcount>
<url>https://www.last.fm/music/Billie+Eilish/WHEN+I+WAS+OLDER+(Music+Inspired+By+The+Film+ROMA)</url>
<artist><name>Billie Eilish</name>
<url>https://www.last.fm/music/Billie+Eilish</url>
</artist>
<image size="small">https://lastfm.freetls.fastly.net/i/u/34s/c5dabfa1f51a1d0ca6ec9f711967a716.png</image>
<image size="medium">https://lastfm.freetls.fastly.net/i/u/64s/c5dabfa1f51a1d0ca6ec9f711967a716.png</image>
<image size="large">https://lastfm.freetls.fastly.net/i/u/174s/c5dabfa1f51a1d0ca6ec9f711967a716.png</image>
<image size="extralarge">https://lastfm.freetls.fastly.net/i/u/300x300/c5dabfa1f51a1d0ca6ec9f711967a716.png</image>
</album>
<album><name>&amp;burn (with Vince Staples)</name>
<playcount>383608</playcount>
<url>https://www.last.fm/music/Billie+Eilish/&amp;burn+(with+Vince+Staples)</url>
<artist><name>Billie Eilish</name>
<url>https://www.last.fm/music/Billie+Eilish</url>
</artist>
<image size="small">https://lastfm.freetls.fastly.net/i/u/34s/e99be294e23e1f97c76055a136ff1d24.png</image>
<image size="medium">https://lastfm.freetls.fastly.net/i/u/64s/e99be294e23e1f97c76055a136ff1d24.png</image>
<image size="large">https://lastfm.freetls.fastly.net/i/u/174s/e99be294e23e1f97c76055a136ff1d24.png</image>
<image size="extralarge">https://lastfm.freetls.fastly.net/i/u/300x300/e99be294e23e1f97c76055a136ff1d24.png</image>
</album>
<album><name>Ocean Eyes</name>
<playcount>350887</playcount>
<url>https://www.last.fm/music/Billie+Eilish/Ocean+Eyes</url>
<artist><name>Billie Eilish</name>
<url>https://www.last.fm/music/Billie+Eilish</url>
</artist>
<image size="small">https://lastfm.freetls.fastly.net/i/u/34s/27d83f93d2c848c70354aaf771b103eb.png</image>
<image size="medium">https://lastfm.freetls.fastly.net/i/u/64s/27d83f93d2c848c70354aaf771b103eb.png</image>
<image size="large">https://lastfm.freetls.fastly.net/i/u/174s/27d83f93d2c848c70354aaf771b103eb.png</image>
<image size="extralarge">https://lastfm.freetls.fastly.net/i/u/300x300/27d83f93d2c848c70354aaf771b103eb.png</image>
</album>
<album><name>Wish You Were Gay</name>
<playcount>424658</playcount>
<url>https://www.last.fm/music/Billie+Eilish/Wish+You+Were+Gay</url>
<artist><name>Billie Eilish</name>
<url>https://www.last.fm/music/Billie+Eilish</url>
</artist>
<image size="small">https://lastfm.freetls.fastly.net/i/u/34s/675641fef94bfb0e71c1d5eac3e64648.png</image>
<image size="medium">https://lastfm.freetls.fastly.net/i/u/64s/675641fef94bfb0e71c1d5eac3e64648.png</image>
<image size="large">https://lastfm.freetls.fastly.net/i/u/174s/675641fef94bfb0e71c1d5eac3e64648.png</image>
<image size="extralarge">https://lastfm.freetls.fastly.net/i/u/300x300/675641fef94bfb0e71c1d5eac3e64648.png</image>
</album>
<album><name>MyBoi (TroyBoi Remix)</name>
<playcount>220463</playcount>
<url>https://www.last.fm/music/Billie+Eilish/MyBoi+(TroyBoi+Remix)</url>
<artist><name>Billie Eilish</name>
<url>https://www.last.fm/music/Billie+Eilish</url>
</artist>
<image size="small">https://lastfm.freetls.fastly.net/i/u/34s/9dbc3aa772e6a973d5bd7338fb3361d3.png</image>
<image size="medium">https://lastfm.freetls.fastly.net/i/u/64s/9dbc3aa772e6a973d5bd7338fb3361d3.png</image>
<image size="large">https://lastfm.freetls.fastly.net/i/u/174s/9dbc3aa772e6a973d5bd7338fb3361d3.png</image>
<image size="extralarge">https://lastfm.freetls.fastly.net/i/u/300x300/9dbc3aa772e6a973d5bd7338fb3361d3.png</image>
</album>
<album><name>COPYCAT (Sofi Tukker Remix)</name>
<playcount>243653</playcount>
<url>https://www.last.fm/music/Billie+Eilish/COPYCAT+(Sofi+Tukker+Remix)</url>
<artist><name>Billie Eilish</name>
<url>https://www.last.fm/music/Billie+Eilish</url>
</artist>
<image size="small">https://lastfm.freetls.fastly.net/i/u/34s/b3052370eb38c06418b558b8bdd6927c.png</image>
<image size="medium">https://lastfm.freetls.fastly.net/i/u/64s/b3052370eb38c06418b558b8bdd6927c.png</image>
<image size="large">https://lastfm.freetls.fastly.net/i/u/174s/b3052370eb38c06418b558b8bdd6927c.png</image>
<image size="extralarge">https://lastfm.freetls.fastly.net/i/u/300x300/b3052370eb38c06418b558b8bdd6927c.png</image>
</album>
<album><name>Bellyache (Marian Hill Remix)</name>
<playcount>240871</playcount>
<url>https://www.last.fm/music/Billie+Eilish/Bellyache+(Marian+Hill+Remix)</url>
<artist><name>Billie Eilish</name>
<url>https://www.last.fm/music/Billie+Eilish</url>
</artist>
<image size="small">https://lastfm.freetls.fastly.net/i/u/34s/6820a7710df7dc0418c2b0971a68988b.png</image>
<image size="medium">https://lastfm.freetls.fastly.net/i/u/64s/6820a7710df7dc0418c2b0971a68988b.png</image>
<image size="large">https://lastfm.freetls.fastly.net/i/u/174s/6820a7710df7dc0418c2b0971a68988b.png</image>
<image size="extralarge">https://lastfm.freetls.fastly.net/i/u/300x300/6820a7710df7dc0418c2b0971a68988b.png</image>
</album>
<album><name>(null)</name>
<playcount>1336760</playcount>
<url>https://www.last.fm/music/Billie+Eilish/(null)</url>
<artist><name>Billie Eilish</name>
<url>https://www.last.fm/music/Billie+Eilish</url>
</artist>
<image size="small"></image>
<image size="medium"></image>
<image size="large"></image>
<image size="extralarge"></image>
</album>
<album><name>Six Feet Under (The Remixes)</name>
<playcount>230457</playcount>
<url>https://www.last.fm/music/Billie+Eilish/Six+Feet+Under+(The+Remixes)</url>
<artist><name>Billie Eilish</name>
<url>https://www.last.fm/music/Billie+Eilish</url>
</artist>
<image size="small">https://lastfm.freetls.fastly.net/i/u/34s/714a9febeb71875c84873d2bee92b9d5.png</image>
<image size="medium">https://lastfm.freetls.fastly.net/i/u/64s/714a9febeb71875c84873d2bee92b9d5.png</image>
<image size="large">https://lastfm.freetls.fastly.net/i/u/174s/714a9febeb71875c84873d2bee92b9d5.png</image>
<image size="extralarge">https://lastfm.freetls.fastly.net/i/u/300x300/714a9febeb71875c84873d2bee92b9d5.png</image>
</album>
<album><name>dont smile at me (Expanded Edition)</name>
<playcount>375948</playcount>
<url>https://www.last.fm/music/Billie+Eilish/dont+smile+at+me+(Expanded+Edition)</url>
<artist><name>Billie Eilish</name>
<url>https://www.last.fm/music/Billie+Eilish</url>
</artist>
<image size="small">https://lastfm.freetls.fastly.net/i/u/34s/99c5c6cc986b4b3e49567a64887cc956.png</image>
<image size="medium">https://lastfm.freetls.fastly.net/i/u/64s/99c5c6cc986b4b3e49567a64887cc956.png</image>
<image size="large">https://lastfm.freetls.fastly.net/i/u/174s/99c5c6cc986b4b3e49567a64887cc956.png</image>
<image size="extralarge">https://lastfm.freetls.fastly.net/i/u/300x300/99c5c6cc986b4b3e49567a64887cc956.png</image>
</album>
<album><name>Ocean Eyes (Astronomyy Edit)</name>
<playcount>116943</playcount>
<url>https://www.last.fm/music/Billie+Eilish/Ocean+Eyes+(Astronomyy+Edit)</url>
<artist><name>Billie Eilish</name>
<url>https://www.last.fm/music/Billie+Eilish</url>
</artist>
<image size="small">https://lastfm.freetls.fastly.net/i/u/34s/7895edfa6a1959c9062399836ea72139.png</image>
<image size="medium">https://lastfm.freetls.fastly.net/i/u/64s/7895edfa6a1959c9062399836ea72139.png</image>
<image size="large">https://lastfm.freetls.fastly.net/i/u/174s/7895edfa6a1959c9062399836ea72139.png</image>
<image size="extralarge">https://lastfm.freetls.fastly.net/i/u/300x300/7895edfa6a1959c9062399836ea72139.png</image>
</album>
<album><name>lovely</name>
<playcount>123777</playcount>
<url>https://www.last.fm/music/Billie+Eilish/lovely</url>
<artist><name>Billie Eilish</name>
<url>https://www.last.fm/music/Billie+Eilish</url>
</artist>
<image size="small">https://lastfm.freetls.fastly.net/i/u/34s/a9673db742a73e38851871dfd3c7f4bd.png</image>
<image size="medium">https://lastfm.freetls.fastly.net/i/u/64s/a9673db742a73e38851871dfd3c7f4bd.png</image>
<image size="large">https://lastfm.freetls.fastly.net/i/u/174s/a9673db742a73e38851871dfd3c7f4bd.png</image>
<image size="extralarge">https://lastfm.freetls.fastly.net/i/u/300x300/a9673db742a73e38851871dfd3c7f4bd.png</image>
</album>
<album><name>13 Reasons Why (A Netflix Original Series Soundtrack)</name>
<playcount>101318</playcount>
<url>https://www.last.fm/music/Billie+Eilish/13+Reasons+Why+(A+Netflix+Original+Series+Soundtrack)</url>
<artist><name>Billie Eilish</name>
<url>https://www.last.fm/music/Billie+Eilish</url>
</artist>
<image size="small">https://lastfm.freetls.fastly.net/i/u/34s/676c8aece7f72732cb74ac047c916c92.png</image>
<image size="medium">https://lastfm.freetls.fastly.net/i/u/64s/676c8aece7f72732cb74ac047c916c92.png</image>
<image size="large">https://lastfm.freetls.fastly.net/i/u/174s/676c8aece7f72732cb74ac047c916c92.png</image>
<image size="extralarge">https://lastfm.freetls.fastly.net/i/u/300x300/676c8aece7f72732cb74ac047c916c92.png</image>
</album>
<album><name>everything i wanted - Single</name>
<playcount>219256</playcount>
<url>https://www.last.fm/music/Billie+Eilish/everything+i+wanted+-+Single</url>
<artist><name>Billie Eilish</name>
<url>https://www.last.fm/music/Billie+Eilish</url>
</artist>
<image size="small">https://lastfm.freetls.fastly.net/i/u/34s/c6edb18d72722777943d16dc132a1456.png</image>
<image size="medium">https://lastfm.freetls.fastly.net/i/u/64s/c6edb18d72722777943d16dc132a1456.png</image>
<image size="large">https://lastfm.freetls.fastly.net/i/u/174s/c6edb18d72722777943d16dc132a1456.png</image>
<image size="extralarge">https://lastfm.freetls.fastly.net/i/u/300x300/c6edb18d72722777943d16dc132a1456.png</image>
</album>
<album><name>watch</name>
<playcount>29745</playcount>
<url>https://www.last.fm/music/Billie+Eilish/watch</url>
<artist><name>Billie Eilish</name>
<url>https://www.last.fm/music/Billie+Eilish</url>
</artist>
<image size="small">https://lastfm.freetls.fastly.net/i/u/34s/c22d859d6561f90f7bcb1238fd45022f.png</image>
<image size="medium">https://lastfm.freetls.fastly.net/i/u/64s/c22d859d6561f90f7bcb1238fd45022f.png</image>
<image size="large">https://lastfm.freetls.fastly.net/i/u/174s/c22d859d6561f90f7bcb1238fd45022f.png</image>
<image size="extralarge">https://lastfm.freetls.fastly.net/i/u/300x300/c22d859d6561f90f7bcb1238fd45022f.png</image>
</album>
<album><name>No Time To Die - Single</name>
<playcount>79534</playcount>
<url>https://www.last.fm/music/Billie+Eilish/No+Time+To+Die+-+Single</url>
<artist><name>Billie Eilish</name>
<url>https://www.last.fm/music/Billie+Eilish</url>
</artist>
<image size="small">https://lastfm.freetls.fastly.net/i/u/34s/3b9840a25e7ebce5da9193c57ddc8a63.png</image>
<image size="medium">https://lastfm.freetls.fastly.net/i/u/64s/3b9840a25e7ebce5da9193c57ddc8a63.png</image>
<image size="large">https://lastfm.freetls.fastly.net/i/u/174s/3b9840a25e7ebce5da9193c57ddc8a63.png</image>
<image size="extralarge">https://lastfm.freetls.fastly.net/i/u/300x300/3b9840a25e7ebce5da9193c57ddc8a63.png</image>
</album>
<album><name>when the party&apos;s over - single</name>
<playcount>64392</playcount>
<url>https://www.last.fm/music/Billie+Eilish/when+the+party%27s+over+-+single</url>
<artist><name>Billie Eilish</name>
<url>https://www.last.fm/music/Billie+Eilish</url>
</artist>
<image size="small">https://lastfm.freetls.fastly.net/i/u/34s/89f09b4ffe943812f1d0fd9ff95a2bb0.png</image>
<image size="medium">https://lastfm.freetls.fastly.net/i/u/64s/89f09b4ffe943812f1d0fd9ff95a2bb0.png</image>
<image size="large">https://lastfm.freetls.fastly.net/i/u/174s/89f09b4ffe943812f1d0fd9ff95a2bb0.png</image>
<image size="extralarge">https://lastfm.freetls.fastly.net/i/u/300x300/89f09b4ffe943812f1d0fd9ff95a2bb0.png</image>
</album>
<album><name>don&apos;t smile at me</name>
<playcount>159501</playcount>
<url>https://www.last.fm/music/Billie+Eilish/don%27t+smile+at+me</url>
<artist><name>Billie Eilish</name>
<url>https://www.last.fm/music/Billie+Eilish</url>
</artist>
<image size="small">https://lastfm.freetls.fastly.net/i/u/34s/93860c6239468595a653609c01a90307.png</image>
<image size="medium">https://lastfm.freetls.fastly.net/i/u/64s/93860c6239468595a653609c01a90307.png</image>
<image size="large">https://lastfm.freetls.fastly.net/i/u/174s/93860c6239468595a653609c01a90307.png</image>
<image size="extralarge">https://lastfm.freetls.fastly.net/i/u/300x300/93860c6239468595a653609c01a90307.png</image>
</album>
<album><name>Now That&apos;s What I Call Music, Vol. 71</name>
<playcount>18463</playcount>
<url>https://www.last.fm/music/Billie+Eilish/Now+That%27s+What+I+Call+Music,+Vol.+71</url>
<artist><name>Billie Eilish</name>
<url>https://www.last.fm/music/Billie+Eilish</url>
</artist>
<image size="small"></image>
<image size="medium"></image>
<image size="large"></image>
<image size="extralarge"></image>
</album>
<album><name>come out and play - Single</name>
<playcount>64981</playcount>
<url>https://www.last.fm/music/Billie+Eilish/come+out+and+play+-+Single</url>
<artist><name>Billie Eilish</name>
<url>https://www.last.fm/music/Billie+Eilish</url>
</artist>
<image size="small">https://lastfm.freetls.fastly.net/i/u/34s/c9fa8d14b28f6f966e7dbc2ecd01b0f8.png</image>
<image size="medium">https://lastfm.freetls.fastly.net/i/u/64s/c9fa8d14b28f6f966e7dbc2ecd01b0f8.png</image>
<image size="large">https://lastfm.freetls.fastly.net/i/u/174s/c9fa8d14b28f6f966e7dbc2ecd01b0f8.png</image>
<image size="extralarge">https://lastfm.freetls.fastly.net/i/u/300x300/c9fa8d14b28f6f966e7dbc2ecd01b0f8.png</image>
</album>
<album><name>13 Reasons Why (Season 2)</name>
<playcount>20428</playcount>
<url>https://www.last.fm/music/Billie+Eilish/13+Reasons+Why+(Season+2)</url>
<artist><name>Billie Eilish</name>
<url>https://www.last.fm/music/Billie+Eilish</url>
</artist>
<image size="small">https://lastfm.freetls.fastly.net/i/u/34s/599b7ca87237ac2d1556a028c7b088b9.png</image>
<image size="medium">https://lastfm.freetls.fastly.net/i/u/64s/599b7ca87237ac2d1556a028c7b088b9.png</image>
<image size="large">https://lastfm.freetls.fastly.net/i/u/174s/599b7ca87237ac2d1556a028c7b088b9.png</image>
<image size="extralarge">https://lastfm.freetls.fastly.net/i/u/300x300/599b7ca87237ac2d1556a028c7b088b9.png</image>
</album>
<album><name>Bitches Broken Hearts - Single</name>
<playcount>58668</playcount>
<url>https://www.last.fm/music/Billie+Eilish/Bitches+Broken+Hearts+-+Single</url>
<artist><name>Billie Eilish</name>
<url>https://www.last.fm/music/Billie+Eilish</url>
</artist>
<image size="small">https://lastfm.freetls.fastly.net/i/u/34s/f8abad9f807e55f4cdf77cf60b2e32a8.png</image>
<image size="medium">https://lastfm.freetls.fastly.net/i/u/64s/f8abad9f807e55f4cdf77cf60b2e32a8.png</image>
<image size="large">https://lastfm.freetls.fastly.net/i/u/174s/f8abad9f807e55f4cdf77cf60b2e32a8.png</image>
<image size="extralarge">https://lastfm.freetls.fastly.net/i/u/300x300/f8abad9f807e55f4cdf77cf60b2e32a8.png</image>
</album>
<album><name>When We All Fall Asleep Where Do We Go?</name>
<playcount>63004</playcount>
<url>https://www.last.fm/music/Billie+Eilish/When+We+All+Fall+Asleep+Where+Do+We+Go%3F</url>
<artist><name>Billie Eilish</name>
<url>https://www.last.fm/music/Billie+Eilish</url>
</artist>
<image size="small">https://lastfm.freetls.fastly.net/i/u/34s/dd6003e64c1d53ba2cebc726560afe98.png</image>
<image size="medium">https://lastfm.freetls.fastly.net/i/u/64s/dd6003e64c1d53ba2cebc726560afe98.png</image>
<image size="large">https://lastfm.freetls.fastly.net/i/u/174s/dd6003e64c1d53ba2cebc726560afe98.png</image>
<image size="extralarge">https://lastfm.freetls.fastly.net/i/u/300x300/dd6003e64c1d53ba2cebc726560afe98.png</image>
</album>
<album><name>my future - Single</name>
<playcount>53997</playcount>
<url>https://www.last.fm/music/Billie+Eilish/my+future+-+Single</url>
<artist><name>Billie Eilish</name>
<url>https://www.last.fm/music/Billie+Eilish</url>
</artist>
<image size="small">https://lastfm.freetls.fastly.net/i/u/34s/0072132ebbe917879f0c6bc3aa68be3a.png</image>
<image size="medium">https://lastfm.freetls.fastly.net/i/u/64s/0072132ebbe917879f0c6bc3aa68be3a.png</image>
<image size="large">https://lastfm.freetls.fastly.net/i/u/174s/0072132ebbe917879f0c6bc3aa68be3a.png</image>
<image size="extralarge">https://lastfm.freetls.fastly.net/i/u/300x300/0072132ebbe917879f0c6bc3aa68be3a.png</image>
</album>
<album><name>Ocean Eyes (Blackbear Remix)</name>
<playcount>22546</playcount>
<url>https://www.last.fm/music/Billie+Eilish/Ocean+Eyes+(Blackbear+Remix)</url>
<artist><name>Billie Eilish</name>
<url>https://www.last.fm/music/Billie+Eilish</url>
</artist>
<image size="small"></image>
<image size="medium"></image>
<image size="large"></image>
<image size="extralarge"></image>
</album>
<album><name>Now That&apos;s What I Call Music!, Vol. 70</name>
<playcount>12900</playcount>
<url>https://www.last.fm/music/Billie+Eilish/Now+That%27s+What+I+Call+Music%21,+Vol.+70</url>
<artist><name>Billie Eilish</name>
<url>https://www.last.fm/music/Billie+Eilish</url>
</artist>
<image size="small">https://lastfm.freetls.fastly.net/i/u/34s/45f39c6c875e7b012e7f43e87756cdd1.png</image>
<image size="medium">https://lastfm.freetls.fastly.net/i/u/64s/45f39c6c875e7b012e7f43e87756cdd1.png</image>
<image size="large">https://lastfm.freetls.fastly.net/i/u/174s/45f39c6c875e7b012e7f43e87756cdd1.png</image>
<image size="extralarge">https://lastfm.freetls.fastly.net/i/u/300x300/45f39c6c875e7b012e7f43e87756cdd1.png</image>
</album>
<album><name>Now 34</name>
<playcount>13316</playcount>
<url>https://www.last.fm/music/Billie+Eilish/Now+34</url>
<artist><name>Billie Eilish</name>
<url>https://www.last.fm/music/Billie+Eilish</url>
</artist>
<image size="small"></image>
<image size="medium"></image>
<image size="large"></image>
<image size="extralarge"></image>
</album>
<album><name>you should see me in a crown - Single</name>
<playcount>41489</playcount>
<url>https://www.last.fm/music/Billie+Eilish/you+should+see+me+in+a+crown+-+Single</url>
<artist><name>Billie Eilish</name>
<url>https://www.last.fm/music/Billie+Eilish</url>
</artist>
<image size="small">https://lastfm.freetls.fastly.net/i/u/34s/19a0cee7b057074e31d9d723be5a6ee0.png</image>
<image size="medium">https://lastfm.freetls.fastly.net/i/u/64s/19a0cee7b057074e31d9d723be5a6ee0.png</image>
<image size="large">https://lastfm.freetls.fastly.net/i/u/174s/19a0cee7b057074e31d9d723be5a6ee0.png</image>
<image size="extralarge">https://lastfm.freetls.fastly.net/i/u/300x300/19a0cee7b057074e31d9d723be5a6ee0.png</image>
</album>
<album><name>bad guy</name>
<playcount>13148</playcount>
<url>https://www.last.fm/music/Billie+Eilish/bad+guy</url>
<artist><name>Billie Eilish</name>
<url>https://www.last.fm/music/Billie+Eilish</url>
</artist>
<image size="small">https://lastfm.freetls.fastly.net/i/u/34s/3dd952438aaeaa69c7ee6860cc6831d1.png</image>
<image size="medium">https://lastfm.freetls.fastly.net/i/u/64s/3dd952438aaeaa69c7ee6860cc6831d1.png</image>
<image size="large">https://lastfm.freetls.fastly.net/i/u/174s/3dd952438aaeaa69c7ee6860cc6831d1.png</image>
<image size="extralarge">https://lastfm.freetls.fastly.net/i/u/300x300/3dd952438aaeaa69c7ee6860cc6831d1.png</image>
</album>
<album><name>Now That&apos;s What I Call Music!, Vol. 81</name>
<playcount>11483</playcount>
<url>https://www.last.fm/music/Billie+Eilish/Now+That%27s+What+I+Call+Music%21,+Vol.+81</url>
<artist><name>Billie Eilish</name>
<url>https://www.last.fm/music/Billie+Eilish</url>
</artist>
<image size="small">https://lastfm.freetls.fastly.net/i/u/34s/06907f1c4e061889d1110a6c5b41b292.png</image>
<image size="medium">https://lastfm.freetls.fastly.net/i/u/64s/06907f1c4e061889d1110a6c5b41b292.png</image>
<image size="large">https://lastfm.freetls.fastly.net/i/u/174s/06907f1c4e061889d1110a6c5b41b292.png</image>
<image size="extralarge">https://lastfm.freetls.fastly.net/i/u/300x300/06907f1c4e061889d1110a6c5b41b292.png</image>
</album>
<album><name>Six Feet Under - Single</name>
<playcount>35690</playcount>
<url>https://www.last.fm/music/Billie+Eilish/Six+Feet+Under+-+Single</url>
<artist><name>Billie Eilish</name>
<url>https://www.last.fm/music/Billie+Eilish</url>
</artist>
<image size="small">https://lastfm.freetls.fastly.net/i/u/34s/da8f167b68507f3cbf9568b2808bbdb2.png</image>
<image size="medium">https://lastfm.freetls.fastly.net/i/u/64s/da8f167b68507f3cbf9568b2808bbdb2.png</image>
<image size="large">https://lastfm.freetls.fastly.net/i/u/174s/da8f167b68507f3cbf9568b2808bbdb2.png</image>
<image size="extralarge">https://lastfm.freetls.fastly.net/i/u/300x300/da8f167b68507f3cbf9568b2808bbdb2.png</image>
</album>
<album><name>WHEN I WAS OLDER</name>
<playcount>12819</playcount>
<url>https://www.last.fm/music/Billie+Eilish/WHEN+I+WAS+OLDER</url>
<artist><name>Billie Eilish</name>
<url>https://www.last.fm/music/Billie+Eilish</url>
</artist>
<image size="small">https://lastfm.freetls.fastly.net/i/u/34s/ced97a852f07996ffead674b7c07dc27.png</image>
<image size="medium">https://lastfm.freetls.fastly.net/i/u/64s/ced97a852f07996ffead674b7c07dc27.png</image>
<image size="large">https://lastfm.freetls.fastly.net/i/u/174s/ced97a852f07996ffead674b7c07dc27.png</image>
<image size="extralarge">https://lastfm.freetls.fastly.net/i/u/300x300/ced97a852f07996ffead674b7c07dc27.png</image>
</album>
<album><name>WHEN I WAS OLDER (Music Inspired by the Film &quot;ROMA&quot;) - Single</name>
<playcount>23949</playcount>
<url>https://www.last.fm/music/Billie+Eilish/WHEN+I+WAS+OLDER+(Music+Inspired+by+the+Film+%22ROMA%22)+-+Single</url>
<artist><name>Billie Eilish</name>
<url>https://www.last.fm/music/Billie+Eilish</url>
</artist>
<image size="small">https://lastfm.freetls.fastly.net/i/u/34s/6d65c70781325ab912cd8a20de6caea1.png</image>
<image size="medium">https://lastfm.freetls.fastly.net/i/u/64s/6d65c70781325ab912cd8a20de6caea1.png</image>
<image size="large">https://lastfm.freetls.fastly.net/i/u/174s/6d65c70781325ab912cd8a20de6caea1.png</image>
<image size="extralarge">https://lastfm.freetls.fastly.net/i/u/300x300/6d65c70781325ab912cd8a20de6caea1.png</image>
</album>
<album><name>We Love Summer 2019 [Explicit]</name>
<playcount>5675</playcount>
<url>https://www.last.fm/music/Billie+Eilish/We+Love+Summer+2019+%5BExplicit%5D</url>
<artist><name>Billie Eilish</name>
<url>https://www.last.fm/music/Billie+Eilish</url>
</artist>
<image size="small"></image>
<image size="medium"></image>
<image size="large"></image>
<image size="extralarge"></image>
</album>
</topalbums>
</lfm>
