<?xml version="1.0" encoding="UTF-8" ?>
<lfm status="ok"><artist><name>The Smiths</name>
<mbid>40f5d9e4-2de7-4f2d-ad41-e31a9a9fea27</mbid>
<url>https://www.last.fm/music/The+Smiths</url>
<image size="small">https://lastfm.freetls.fastly.net/i/u/34s/2a96cbd8b46e442fc41c2b86b821562f.png</image>
<image size="medium">https://lastfm.freetls.fastly.net/i/u/64s/2a96cbd8b46e442fc41c2b86b821562f.png</image>
<image size="large">https://lastfm.freetls.fastly.net/i/u/174s/2a96cbd8b46e442fc41c2b86b821562f.png</image>
<image size="extralarge">https://lastfm.freetls.fastly.net/i/u/300x300/2a96cbd8b46e442fc41c2b86b821562f.png</image>
<image size="mega">https://lastfm.freetls.fastly.net/i/u/300x300/2a96cbd8b46e442fc41c2b86b821562f.png</image>
<image size="">https://lastfm.freetls.fastly.net/i/u/300x300/2a96cbd8b46e442fc41c2b86b821562f.png</image>
<streamable>0</streamable>
<ontour>0</ontour>
<stats><listeners>2480284</listeners>
<playcount>175769552</playcount>
</stats>
<similar><artist><name>Morrissey</name>
<url>https://www.last.fm/music/Morrissey</url>
<image size="small">https://lastfm.freetls.fastly.net/i/u/34s/2a96cbd8b46e442fc41c2b86b821562f.png</image>
<image size="medium">https://lastfm.freetls.fastly.net/i/u/64s/2a96cbd8b46e442fc41c2b86b821562f.png</image>
<image size="large">https://lastfm.freetls.fastly.net/i/u/174s/2a96cbd8b46e442fc41c2b86b821562f.png</image>
<image size="extralarge">https://lastfm.freetls.fastly.net/i/u/300x300/2a96cbd8b46e442fc41c2b86b821562f.png</image>
<image size="mega">https://lastfm.freetls.fastly.net/i/u/300x300/2a96cbd8b46e442fc41c2b86b821562f.png</image>
<image size="">https://lastfm.freetls.fastly.net/i/u/300x300/2a96cbd8b46e442fc41c2b86b821562f.png</image>
</artist>
<artist><name>Joy Division</name>
<url>https://www.last.fm/music/Joy+Division</url>
<image size="small">https://lastfm.freetls.fastly.net/i/u/34s/2a96cbd8b46e442fc41c2b86b821562f.png</image>
<image size="medium">https://lastfm.freetls.fastly.net/i/u/64s/2a96cbd8b46e442fc41c2b86b821562f.png</image>
<image size="large">https://lastfm.freetls.fastly.net/i/u/174s/2a96cbd8b46e442fc41c2b86b821562f.png</image>
<image size="extralarge">https://lastfm.freetls.fastly.net/i/u/300x300/2a96cbd8b46e442fc41c2b86b821562f.png</image>
<image size="mega">https://lastfm.freetls.fastly.net/i/u/300x300/2a96cbd8b46e442fc41c2b86b821562f.png</image>
<image size="">https://lastfm.freetls.fastly.net/i/u/300x300/2a96cbd8b46e442fc41c2b86b821562f.png</image>
</artist>
<artist><name>The Cure</name>
<url>https://www.last.fm/music/The+Cure</url>
<image size="small">https://lastfm.freetls.fastly.net/i/u/34s/2a96cbd8b46e442fc41c2b86b821562f.png</image>
<image size="medium">https://lastfm.freetls.fastly.net/i/u/64s/2a96cbd8b46e442fc41c2b86b821562f.png</image>
<image size="large">https://lastfm.freetls.fastly.net/i/u/174s/2a96cbd8b46e442fc41c2b86b821562f.png</image>
<image size="extralarge">https://lastfm.freetls.fastly.net/i/u/300x300/2a96cbd8b46e442fc41c2b86b821562f.png</image>
<image size="mega">https://lastfm.freetls.fastly.net/i/u/300x300/2a96cbd8b46e442fc41c2b86b821562f.png</image>
<image size="">https://lastfm.freetls.fastly.net/i/u/300x300/2a96cbd8b46e442fc41c2b86b821562f.png</image>
</artist>
<artist><name>New Order</name>
<url>https://www.last.fm/music/New+Order</url>
<image size="small">https://lastfm.freetls.fastly.net/i/u/34s/2a96cbd8b46e442fc41c2b86b821562f.png</image>
<image size="medium">https://lastfm.freetls.fastly.net/i/u/64s/2a96cbd8b46e442fc41c2b86b821562f.png</image>
<image size="large">https://lastfm.freetls.fastly.net/i/u/174s/2a96cbd8b46e442fc41c2b86b821562f.png</image>
<image size="extralarge">https://lastfm.freetls.fastly.net/i/u/300x300/2a96cbd8b46e442fc41c2b86b821562f.png</image>
<image size="mega">https://lastfm.freetls.fastly.net/i/u/300x300/2a96cbd8b46e442fc41c2b86b821562f.png</image>
<image size="">https://lastfm.freetls.fastly.net/i/u/300x300/2a96cbd8b46e442fc41c2b86b821562f.png</image>
</artist>
<artist><name>Talking Heads</name>
<url>https://www.last.fm/music/Talking+Heads</url>
<image size="small">https://lastfm.freetls.fastly.net/i/u/34s/2a96cbd8b46e442fc41c2b86b821562f.png</image>
<image size="medium">https://lastfm.freetls.fastly.net/i/u/64s/2a96cbd8b46e442fc41c2b86b821562f.png</image>
<image size="large">https://lastfm.freetls.fastly.net/i/u/174s/2a96cbd8b46e442fc41c2b86b821562f.png</image>
<image size="extralarge">https://lastfm.freetls.fastly.net/i/u/300x300/2a96cbd8b46e442fc41c2b86b821562f.png</image>
<image size="mega">https://lastfm.freetls.fastly.net/i/u/300x300/2a96cbd8b46e442fc41c2b86b821562f.png</image>
<image size="">https://lastfm.freetls.fastly.net/i/u/300x300/2a96cbd8b46e442fc41c2b86b821562f.png</image>
</artist>
</similar>
<tags><tag><name>indie</name>
<url>https://www.last.fm/tag/indie</url>
</tag>
<tag><name>80s</name>
<url>https://www.last.fm/tag/80s</url>
</tag>
<tag><name>post-punk</name>
<url>https://www.last.fm/tag/post-punk</url>
</tag>
<tag><name>new wave</name>
<url>https://www.last.fm/tag/new+wave</url>
</tag>
<tag><name>alternative</name>
<url>https://www.last.fm/tag/alternative</url>
</tag>
</tags>
<bio><links><link rel="original" href="https://last.fm/music/The+Smiths/+wiki"></link>
</links>
<published>10 Feb 2006, 14:36</published>
<summary>&#10;The Smiths were a rock band which formed in 1982 in Manchester, England, United Kingdom. The band consisted of  Morrissey (vocals, lyrics), Johnny Marr (guitar, music), Mike Joyce (drums) and Andy Rourke (bass). Hugely influential, The Smiths lasted all of five years from 1982 to 1987, releasing during this period four studio albums (The Smiths, Meat Is Murder, The Queen Is Dead and Strangeways, Here We Come) and three compilation albums (Hatful Of Hollow, The World Won&apos;t Listen and Louder Than Bombs). &lt;a href=&quot;https://www.last.fm/music/The+Smiths&quot;&gt;Read more on Last.fm&lt;/a&gt;</summary>
<content>&#10;The Smiths were a rock band which formed in 1982 in Manchester, England, United Kingdom. The band consisted of  Morrissey (vocals, lyrics), Johnny Marr (guitar, music), Mike Joyce (drums) and Andy Rourke (bass). Hugely influential, The Smiths lasted all of five years from 1982 to 1987, releasing during this period four studio albums (The Smiths, Meat Is Murder, The Queen Is Dead and Strangeways, Here We Come) and three compilation albums (Hatful Of Hollow, The World Won&apos;t Listen and Louder Than Bombs). Meat Is Murder went on to enter the British charts at number one in February of 1985, and The Queen Is Dead further confirmed the band&apos;s popularity with its release in spring 1986. Greeted with enthusiastic reviews and peaking at number two on the U.K. charts, the album also developed The Smiths&apos; cult following in the U.S., breaking into the Top 100.&#10;&#10;After the band&apos;s split in 1987, a further six albums have been released, bringing the total number of Smiths albums to 13. These albums consisted of another five compilation albums (Best... I, ...Best II, Singles, The Very Best of the Smiths and The Sound of the Smiths), and one live album (Rank) recorded before the band&apos;s split during The Queen Is Dead tour. Both &quot;Best I&quot; and &quot;Best II&quot; were heavily criticised by critics and some fans; &quot;The Very Best of&quot;, was very similar content to said &quot;Best&quot; albums, sold excellently, but drew much criticism from press and the band, who had no input.&#10;&#10;Former members&#10;&#10;Bass was originally played by Dale Hibbert, but he was replaced after 4 months. Craig Gannon was briefly a second guitarist for the band in 1986.&#10;See The Smiths First Meetings &#10; &lt;a href=&quot;https://www.last.fm/music/The+Smiths&quot;&gt;Read more on Last.fm&lt;/a&gt;. User-contributed text is available under the Creative Commons By-SA License; additional terms may apply.</content>
</bio>
</artist>
</lfm>
